newproject/__init__.py
newproject/main.py
newproject/project.py
newproject/template.py
newproject/util.py
pursuit_newproject-0.1.1.dist-info/LICENSE
pursuit_newproject-0.1.1.dist-info/METADATA
pursuit_newproject-0.1.1.dist-info/WHEEL
pursuit_newproject-0.1.1.dist-info/entry_points.txt
pursuit_newproject-0.1.1.dist-info/top_level.txt
pursuit_newproject-0.1.1.dist-info/RECORD
