Metadata-Version: 2.1
Name: pursuit-newproject
Version: 0.1.1
Summary: Project templater
Home-page: https://gitlab.com/frPursuit/newproject
Author: Pursuit
Author-email: fr.pursuit@gmail.com
License: GNU General Public License v3 (GPLv3)
Classifier: Programming Language :: Python :: 3
Classifier: License :: OSI Approved :: GNU General Public License v3 (GPLv3)
Classifier: Operating System :: OS Independent
Requires-Python: >=3.7
License-File: LICENSE
Requires-Dist: Jinja2 (>=3.1.2)
Requires-Dist: PyYAML (>=6.0)
